daemons/__init__.py
daemons/daemonizer.py
daemons/daemonize/__init__.py
daemons/daemonize/noop.py
daemons/daemonize/simple.py
daemons/interfaces/__init__.py
daemons/interfaces/daemonize.py
daemons/interfaces/exit.py
daemons/interfaces/message.py
daemons/interfaces/pid.py
daemons/interfaces/signal.py
daemons/interfaces/startstop.py
daemons/message/__init__.py
daemons/message/eventlet.py
daemons/message/gevent.py
daemons/pid/__init__.py
daemons/pid/simple.py
daemons/prefab/__init__.py
daemons/prefab/eventletd.py
daemons/prefab/geventd.py
daemons/prefab/run.py
daemons/prefab/step.py
daemons/signal/__init__.py
daemons/signal/simple.py
daemons/startstop/__init__.py
daemons/startstop/simple.py
daemons-1.3.1.dist-info/LICENSE
daemons-1.3.1.dist-info/METADATA
daemons-1.3.1.dist-info/WHEEL
daemons-1.3.1.dist-info/top_level.txt
daemons-1.3.1.dist-info/RECORD
