Metadata-Version: 1.0
Name: daemons
Version: 1.3.1
Summary: Well behaved unix daemons for every occasion.
Home-page: https://github.com/kevinconway/daemons
Author: Kevin Conway
Author-email: kevinjacobconway@gmail.com
License: 'Apache License 2.0
Platform: UNKNOWN
